microwatt_dft.v
module microwatt_dft (
    input  wire       clk,
    input  wire       rst,
    input  wire       scan_en,
    input  wire       scan_in,
    output wire       scan_out,
    output wire       bist_done,
    output wire       bist_fail
);
    // simple 4-bit scan-register example
    reg [3:0] q;
    wire [3:0] d;

    always @(posedge clk or posedge rst) begin
        if (rst)
            q <= 4'b0000;
        else if (scan_en)
            q <= {q[2:0], scan_in};
        else
            q <= d;
    end

    assign scan_out = q[3];

    // pretend MBIST controller logic (placeholder)
    assign d = q + 1;
    assign bist_done = 1'b1;
    assign bist_fail = 1'b0;
endmodule

tb_microwatt_dft.v
`timescale 1ns/1ps

module tb_microwatt_dft;
    reg clk, rst, scan_en, scan_in;
    wire scan_out;
    wire bist_done, bist_fail;

    microwatt_dft dut (
        .clk(clk),
        .rst(rst),
        .scan_en(scan_en),
        .scan_in(scan_in),
        .scan_out(scan_out),
        .bist_done(bist_done),
        .bist_fail(bist_fail)
    );

    initial clk = 0;
    always #5 clk = ~clk; // 100 MHz

    initial begin
   $dumpfile("opendft.vcd");
    $dumpvars(0, tb_microwatt_dft);
        rst = 1;
        scan_en = 0;
        scan_in = 0;
        #20;
        rst = 0;

        // scan shift some pattern
        scan_en = 1;
        scan_in = 1; #10;
        scan_in = 0; #10;
        scan_in = 1; #10;
        scan_in = 1; #10;
        scan_en = 0;

        #100;
        $finish;
    end
endmodule

opendft.vcd
$date
	Tue Nov  4 03:31:10 2025
$end
$version
	Icarus Verilog
$end
$timescale
	1ps
$end
$scope module tb_microwatt_dft $end
$var wire 1 ! bist_done $end
$var wire 1 " bist_fail $end
$var wire 1 # scan_out $end
$var reg 1 $ clk $end
$var reg 1 % rst $end
$var reg 1 & scan_en $end
$var reg 1 ' scan_in $end
$scope module dut $end
$var wire 1 ! bist_done $end
$var wire 1 " bist_fail $end
$var wire 1 $ clk $end
$var wire 1 % rst $end
$var wire 1 & scan_en $end
$var wire 1 ' scan_in $end
$var wire 1 # scan_out $end
$var wire 4 ( d [3:0] $end
$var reg 4 ) q [3:0] $end
$upscope $end
$upscope $end
$enddefinitions $end
$comment Show the parameter values. $end
$dumpall
$end
#0
$dumpvars
b0 )
b1 (
0'
0&
1%
0$
0#
0"
1!
$end
#5000
1$
#10000
0$
#15000
1$
#20000
0$
1'
1&
0%
#25000
b10 (
b1 )
1$
#30000
0$
0'
#35000
b11 (
b10 )
1$
#40000
0$
1'
#45000
b110 (
b101 )
1$
#50000
0$
#55000
1#
b1100 (
b1011 )
1$
#60000
0$
0&
#65000
b1101 (
b1100 )
1$
#70000
0$
#75000
b1110 (
b1101 )
1$
#80000
0$
#85000
b1111 (
b1110 )
1$
#90000
0$
#95000
b0 (
b1111 )
1$
#100000
0$
#105000
0#
b1 (
b0 )
1$
#110000
0$
#115000
b10 (
b1 )
1$
#120000
0$
#125000
b11 (
b10 )
1$
#130000
0$
#135000
b100 (
b11 )
1$
#140000
0$
#145000
b101 (
b100 )
1$
#150000
0$
#155000
b110 (
b101 )
1$
